string_thing/__init__.py
string_thing/string_thing.py
string_thing-1.0.1.dist-info/METADATA
string_thing-1.0.1.dist-info/WHEEL
string_thing-1.0.1.dist-info/top_level.txt
string_thing-1.0.1.dist-info/RECORD
