Metadata-Version: 2.1
Name: string-thing
Version: 1.0.1
Summary: A lightweight library for encoding and decoding strings using various patterns.
Home-page: https://github.com/Maxoplata/string-thing-py
Author: Maxamilian Demian
Author-email: max@maxdemian.com
License: MIT
Classifier: Programming Language :: Python
Classifier: Operating System :: OS Independent
Classifier: License :: OSI Approved :: MIT License
Classifier: Intended Audience :: Developers
